django_single_auth/__init__.py
django_single_auth/admin.py
django_single_auth/apps.py
django_single_auth/middleware.py
django_single_auth/models.py
django_single_auth/tests.py
django_single_auth/urls.py
django_single_auth/views.py
django_single_auth/migrations/__init__.py
django_single_auth/server/__init__.py
django_single_auth/server/session.py
django_single_auth/server/token.py
django_single_auth/server/url_manager.py
django_single_auth/static/django_single_auth/css/main.css
django_single_auth/static/django_single_auth/css/util.css
django_single_auth/static/django_single_auth/fonts/font-awesome-4.7.0/HELP-US-OUT.txt
django_single_auth/static/django_single_auth/fonts/font-awesome-4.7.0/css/font-awesome.css
django_single_auth/static/django_single_auth/fonts/font-awesome-4.7.0/css/font-awesome.min.css
django_single_auth/static/django_single_auth/fonts/font-awesome-4.7.0/fonts/FontAwesome.otf
django_single_auth/static/django_single_auth/fonts/font-awesome-4.7.0/fonts/fontawesome-webfont.eot
django_single_auth/static/django_single_auth/fonts/font-awesome-4.7.0/fonts/fontawesome-webfont.svg
django_single_auth/static/django_single_auth/fonts/font-awesome-4.7.0/fonts/fontawesome-webfont.ttf
django_single_auth/static/django_single_auth/fonts/font-awesome-4.7.0/fonts/fontawesome-webfont.woff
django_single_auth/static/django_single_auth/fonts/font-awesome-4.7.0/fonts/fontawesome-webfont.woff2
django_single_auth/static/django_single_auth/fonts/font-awesome-4.7.0/less/animated.less
django_single_auth/static/django_single_auth/fonts/font-awesome-4.7.0/less/bordered-pulled.less
django_single_auth/static/django_single_auth/fonts/font-awesome-4.7.0/less/core.less
django_single_auth/static/django_single_auth/fonts/font-awesome-4.7.0/less/fixed-width.less
django_single_auth/static/django_single_auth/fonts/font-awesome-4.7.0/less/font-awesome.less
django_single_auth/static/django_single_auth/fonts/font-awesome-4.7.0/less/icons.less
django_single_auth-0.0.4.dist-info/LICENSE
django_single_auth-0.0.4.dist-info/METADATA
django_single_auth-0.0.4.dist-info/WHEEL
django_single_auth-0.0.4.dist-info/top_level.txt
django_single_auth-0.0.4.dist-info/RECORD
