Metadata-Version: 2.1
Name: django-single-auth
Version: 0.0.4
Summary: single auth for all applications.
Home-page: https://github.com/GlibAI/django_authentication
Author: Ajit Mourya
Author-email: ajit@glib.ai
License: UNKNOWN
Platform: UNKNOWN
Classifier: Programming Language :: Python :: 3
Classifier: License :: OSI Approved :: MIT License
Classifier: Operating System :: OS Independent
Requires-Python: >=3.6
Requires-Dist: cryptography (==3.4.6)
Requires-Dist: urllib3 (==1.26.3)
